spilo/__init__.py
spilo/base_client.py
spilo/base_pubsub.py
spilo/channel.py
spilo/event_registry.py
spilo/main.py
spilo/redis_pubsub.py
spilo/sync_redis_pubsub.py
spilo/utils.py
tests/__init__.py
tests/conftest.py
tests/test_base_client.py
tests/test_channel.py
tests/test_pubsub.py
spilo-1.0.0.dist-info/METADATA
spilo-1.0.0.dist-info/WHEEL
spilo-1.0.0.dist-info/top_level.txt
spilo-1.0.0.dist-info/RECORD
