Metadata-Version: 2.1
Name: spilo
Version: 1.0.0
Summary: Lightweight library for developing real time applications
Home-page: https://github.com/GiorgiKhunashvili/spilo
Author: Giorgi Khunashvili
Author-email: gkhunashvili@icloud.com
License: MIT
Classifier: Programming Language :: Python :: 3.7
Requires-Python: >=3.7.0
Requires-Dist: redis ==5.0.1
